{
  "random": {
    "accuracy": "0.45870535714285726",
    "precision": "0.38934659090909096",
    "recall": "0.4544070512820513",
    "f1": "0.349512987012987"
  },
  "threshold": {
    "accuracy": "0.5930803571428571",
    "precision": "0.6440104166666667",
    "recall": "0.7133127289377288",
    "f1": "0.5512220418470418"
  },
  "majority": {
    "accuracy": "0.762872023809524",
    "precision": "0.381436011904762",
    "recall": "0.5",
    "f1": "0.42843896205965165"
  },
  "LinearSVM": {
    "accuracy": "0.762872023809524",
    "precision": "0.381436011904762",
    "recall": "0.5",
    "f1": "0.42843896205965165"
  },
  "Logit": {
    "accuracy": "0.7090029761904761",
    "precision": "0.6041666666666667",
    "recall": "0.7056375915750915",
    "f1": "0.6095314407814407"
  },
  "RandomForest": {
    "accuracy": "0.7767113095238096",
    "precision": "0.5064732142857143",
    "recall": "0.6136675824175825",
    "f1": "0.5459033495240392"
  },
  "MLP": {
    "accuracy": "0.7761904761904764",
    "precision": "0.5406994047619048",
    "recall": "0.640327380952381",
    "f1": "0.5765933140933142"
  },
  "Neural-Detector": {
    "accuracy": "0.7411458333333335",
    "precision": "0.4183321886446888",
    "recall": "0.5106456043956044",
    "f1": "0.45279137529137525"
  },
  "best": {
    "models": [
      "random",
      "threshold",
      "Logit"
    ],
    "f1": 0.6095314407814407
  },
  "features": {
    "slice_vec": [
      "slot",
      "prev"
    ],
    "Confidence featurization": "entity",
    "BoW": false,
    "Entity DB check": false,
    "Context window": "1"
  }
}