{
  "random": {
    "accuracy": "0.5517113095238094",
    "precision": "0.5145833333333334",
    "recall": "0.5863782051282052",
    "f1": "0.46632169913419913"
  },
  "threshold": {
    "accuracy": "0.5930803571428571",
    "precision": "0.6440104166666667",
    "recall": "0.7133127289377288",
    "f1": "0.5512220418470418"
  },
  "majority": {
    "accuracy": "0.762872023809524",
    "precision": "0.381436011904762",
    "recall": "0.5",
    "f1": "0.42843896205965165"
  },
  "LinearSVM": {
    "accuracy": "0.762872023809524",
    "precision": "0.381436011904762",
    "recall": "0.5",
    "f1": "0.42843896205965165"
  },
  "Logit": {
    "accuracy": "0.6800595238095238",
    "precision": "0.55625",
    "recall": "0.6433092948717949",
    "f1": "0.5672602513227514"
  },
  "RandomForest": {
    "accuracy": "0.7419642857142859",
    "precision": "0.4161000457875459",
    "recall": "0.5402815934065934",
    "f1": "0.4574935481185481"
  },
  "MLP": {
    "accuracy": "0.7547619047619049",
    "precision": "0.44694940476190487",
    "recall": "0.5528273809523809",
    "f1": "0.48798851611351607"
  },
  "Neural-Detector": {
    "accuracy": "0.7390625000000002",
    "precision": "0.37978557900432913",
    "recall": "0.4865384615384616",
    "f1": "0.42097894522463486"
  },
  "best": {
    "models": [
      "random",
      "threshold",
      "Logit"
    ],
    "f1": 0.5672602513227514
  },
  "features": {
    "slice_vec": [
      "slot",
      "prev"
    ],
    "Confidence featurization": "entity",
    "BoW": false,
    "Entity DB check": true,
    "Context window": "3"
  }
}