{
  "random": {
    "accuracy": "0.43080357142857145",
    "precision": "0.4342013888888889",
    "recall": "0.500257554945055",
    "f1": "0.3603686550377727"
  },
  "threshold": {
    "accuracy": "0.5930803571428571",
    "precision": "0.6440104166666667",
    "recall": "0.7133127289377288",
    "f1": "0.5512220418470418"
  },
  "majority": {
    "accuracy": "0.762872023809524",
    "precision": "0.381436011904762",
    "recall": "0.5",
    "f1": "0.42843896205965165"
  },
  "LinearSVM": {
    "accuracy": "0.762872023809524",
    "precision": "0.381436011904762",
    "recall": "0.5",
    "f1": "0.42843896205965165"
  },
  "Logit": {
    "accuracy": "0.6072172619047619",
    "precision": "0.5520833333333334",
    "recall": "0.5977449633699634",
    "f1": "0.5197758491508491"
  },
  "RandomForest": {
    "accuracy": "0.761011904761905",
    "precision": "0.4171646062271063",
    "recall": "0.5243818681318682",
    "f1": "0.45890248002316963"
  },
  "MLP": {
    "accuracy": "0.8053571428571431",
    "precision": "0.5310267857142859",
    "recall": "0.6205357142857143",
    "f1": "0.566550579050579"
  },
  "Neural-Detector": {
    "accuracy": "0.7316220238095239",
    "precision": "0.4016989087301588",
    "recall": "0.5066105769230769",
    "f1": "0.43832231944300903"
  },
  "best": {
    "models": [
      "random",
      "threshold",
      "MLP"
    ],
    "f1": 0.566550579050579
  },
  "features": {
    "slice_vec": [
      "entity"
    ],
    "Confidence featurization": "entity",
    "BoW": false,
    "Entity DB check": false,
    "Context window": "5"
  }
}