{
  "random": {
    "accuracy": "0.5458333333333333",
    "precision": "0.4621527777777778",
    "recall": "0.5299793956043956",
    "f1": "0.43577907837776253"
  },
  "threshold": {
    "accuracy": "0.5930803571428571",
    "precision": "0.6440104166666667",
    "recall": "0.7133127289377288",
    "f1": "0.5512220418470418"
  },
  "majority": {
    "accuracy": "0.762872023809524",
    "precision": "0.381436011904762",
    "recall": "0.5",
    "f1": "0.42843896205965165"
  },
  "LinearSVM": {
    "accuracy": "0.762872023809524",
    "precision": "0.381436011904762",
    "recall": "0.5",
    "f1": "0.42843896205965165"
  },
  "Logit": {
    "accuracy": "0.6845238095238096",
    "precision": "0.5614583333333334",
    "recall": "0.645713141025641",
    "f1": "0.5738227513227514"
  },
  "RandomForest": {
    "accuracy": "0.7649553571428573",
    "precision": "0.45120478479853493",
    "recall": "0.5538461538461539",
    "f1": "0.4909130620337517"
  },
  "MLP": {
    "accuracy": "0.7462053571428572",
    "precision": "0.4757812500000001",
    "recall": "0.5729166666666666",
    "f1": "0.5134018759018759"
  },
  "Neural-Detector": {
    "accuracy": "0.7390625000000002",
    "precision": "0.4016605790043291",
    "recall": "0.5099759615384616",
    "f1": "0.4408202150659047"
  },
  "best": {
    "models": [
      "random",
      "threshold",
      "Logit"
    ],
    "f1": 0.5738227513227514
  },
  "features": {
    "slice_vec": [
      "entity",
      "prev",
      "slot"
    ],
    "Confidence featurization": "none",
    "BoW": false,
    "Entity DB check": false,
    "Context window": "2"
  }
}