{
  "random": {
    "accuracy": "0.48779761904761904",
    "precision": "0.5030877976190475",
    "recall": "0.4766655219780219",
    "f1": "0.42271825396825397"
  },
  "threshold": {
    "accuracy": "0.5930803571428571",
    "precision": "0.6440104166666667",
    "recall": "0.7133127289377288",
    "f1": "0.5512220418470418"
  },
  "majority": {
    "accuracy": "0.762872023809524",
    "precision": "0.381436011904762",
    "recall": "0.5",
    "f1": "0.42843896205965165"
  },
  "LinearSVM": {
    "accuracy": "0.762872023809524",
    "precision": "0.381436011904762",
    "recall": "0.5",
    "f1": "0.42843896205965165"
  },
  "Logit": {
    "accuracy": "0.6549107142857142",
    "precision": "0.525",
    "recall": "0.599559294871795",
    "f1": "0.5232487073112073"
  },
  "RandomForest": {
    "accuracy": "0.7621279761904763",
    "precision": "0.45007440476190486",
    "recall": "0.5535714285714286",
    "f1": "0.48980907342976304"
  },
  "MLP": {
    "accuracy": "0.7377976190476191",
    "precision": "0.4783482142857144",
    "recall": "0.5632440476190477",
    "f1": "0.5101011655968551"
  },
  "Neural-Detector": {
    "accuracy": "0.7643601190476192",
    "precision": "0.41752232142857154",
    "recall": "0.5264423076923077",
    "f1": "0.4599372785579682"
  },
  "best": {
    "models": [
      "random",
      "threshold"
    ],
    "f1": 0.5512220418470418
  },
  "features": {
    "slice_vec": [
      "entity",
      "slot"
    ],
    "Confidence featurization": "act",
    "BoW": false,
    "Entity DB check": false,
    "Context window": "4"
  }
}